Workbook

Sheet Oct 2026
C1: income: | D1: 15609.62
C2: bal: | D2: 214.14
C3: expected: | D3: 8500
C4: total of actual expenses: | D4: =SUM(B8:B67) -> 15395.48
A7: Checkbox | B7: Actual | C7: What was Paid | D7: Expected | E7: Date | F7: Type
A8: =TRUE() -> TRUE | B8: 5000 | C8: EF | D8: 5000 | E8: 46300 | F8: Emergency Funds
A9: =TRUE() -> TRUE | B9: 40 | C9: W-Water | E9: 46306 | F9: NEEDS/Drinking Water
A10: =TRUE() -> TRUE | B10: 196 | C10: Eggs & Cream | E10: 46300 | F10: NEEDS/Groceries
A11: =TRUE() -> TRUE | B11: 233.5 | C11: Delemondo + Yakult | E11: 46300 | F11: NEEDS/Groceries
A12: =TRUE() -> TRUE | B12: 1000 | C12: Brace Adj | D12: 1000 | E12: 46300 | F12: NEEDS/Healthcare
A13: =TRUE() -> TRUE | B13: 714.78 | C13: Claude | E13: 46302 | F13: NEEDS/Membership
A14: =TRUE() -> TRUE | B14: 385.87 | C14: Sinigang | E14: 46303 | F14: NEEDS/Palengke
A15: =TRUE() -> TRUE | B15: 203.73 | C15: HeyDay (Fruits, Nutmeg, Pepper Corn) | E15: 46304 | F15: NEEDS/Palengke
A16: =TRUE() -> TRUE | B16: 48.2 | C16: Oregano | E16: 46304 | F16: NEEDS/Palengke
A17: =TRUE() -> TRUE | B17: 145 | C17: W-Sinigang Gulay | E17: 46304 | F17: NEEDS/Palengke
A18: =TRUE() -> TRUE | B18: 25 | C18: W-Sinigang Gulay | E18: 46304 | F18: NEEDS/Palengke
A19: =TRUE() -> TRUE | B19: 220 | C19: Beef | E19: 46306 | F19: NEEDS/Palengke
A20: =TRUE() -> TRUE | B20: 40 | C20: Potato + Onions | E20: 46306 | F20: NEEDS/Palengke
A21: =TRUE() -> TRUE | B21: 38 | C21: Potato + Onions | E21: 46307 | F21: NEEDS/Palengke
A22: =TRUE() -> TRUE | B22: 100 | C22: Puto | E22: 46307 | F22: NEEDS/Palengke
A23: =TRUE() -> TRUE | B23: 40 | C23: W-Pamasahe to Work | E23: 46304 | F23: NEEDS/TranspoWork
A24: =TRUE() -> TRUE | B24: 40 | C24: W-Pamasahe from Work | E24: 46305 | F24: NEEDS/TranspoWork
... A51: =TRUE() -> TRUE | B51: 47 | C51: Scoth Tape | E51: 46300 | F51: WANTS/House Improvement
A52: =TRUE() -> TRUE | B52: 2400 | C52: WiFi Installation | D52: 2500 | E52: 46300 | F52: WANTS/House Improvement
A53: =TRUE() -> TRUE | B53: 55.9 | C53: Windows Seal | E53: 46302 | F53: WANTS/House Improvement
A54: =TRUE() -> TRUE | B54: 36 | C54: Door Seal | E54: 46302 | F54: WANTS/House Improvement
A55: =TRUE() -> TRUE | B55: 64 | C55: Suction Hook | E55: 46302 | F55: WANTS/House Improvement
A56: =TRUE() -> TRUE | B56: 100 | C56: Vacuum | E56: 46302 | F56: WANTS/House Improvement
A57: =TRUE() -> TRUE | B57: 58 | C57: Biya Liquid Eyebrow | E57: 46302 | F57: WANTS/Shopping
A58: =TRUE() -> TRUE | B58: 165.5 | C58: Wig | E58: 46304 | F58: WANTS/Shopping
A59: =TRUE() -> TRUE | B59: 115 | C59: W-Mango | E59: 46305 | F59: WANTS/Shopping
A60: =TRUE() -> TRUE | B60: 55 | C60: W-Trans to Ayala | E60: 46301 | F60: WANTS/TranspoPersonal
A61: =TRUE() -> TRUE | B61: 102 | C61: W-Trans to Alabang | E61: 46301 | F61: WANTS/TranspoPersonal
A62: =TRUE() -> TRUE | B62: -17 | C62: W-Jeep to Pasay | E62: 46302 | F62: WANTS/TranspoPersonal
A63: =TRUE() -> TRUE | B63: 14 | C63: W-Jeep to VTX | E63: 46302 | F63: WANTS/TranspoPersonal
A64: =TRUE() -> TRUE | B64: 45 | C64: W-Jeep to Pasay | E64: 46302 | F64: WANTS/TranspoPersonal
... A67: =TRUE() -> TRUE | B67: 15 | C67: W-Pamasahe to Apt | E67: 46304 | F67: WANTS/TranspoPersonal

Sheet Category Map
A1: CATEGORY MAP — links each Diagnosis line to its matching category in the raw log
A2: Diagnosis Label | B2: Matching Raw-Log Category (Type) | C2: Note
A3: Housing: Rent / Mortgage | B3: NEEDS/HousingRent
A4: Kuryente | B4: NEEDS/Electric
A5: Tubig | B5: NEEDS/Water
A6: Internet | B6: NEEDS/Internet
A7: Drinking water | B7: NEEDS/Drinking Water
A8: Groceries | B8: NEEDS/Groceries
A9: Palengke | B9: NEEDS/Palengke
A10: Transportation to Work | B10: NEEDS/TranspoWork
A11: Healthcare | B11: NEEDS/Healthcare
A12: Education | B12: NEEDS/Education
A13: Communication: Prepaid | B13: NEEDS/Communication
A14: Clothing | B14: NEEDS/Clothing
... A18: Government Contributions | B18: NEEDS/Government
A19: Emergency Fund | B19: Emergency Funds | C19: Log uses 'Emergency Funds' (no Needs/Wants prefix) — mapped as-is
A20: Netflix Subscription | B20: WANTS/Netflix
A21: Youtube Premium | B21: WANTS/Youtube
A22: subcription icloud | B22: WANTS/iCloud
A23: Apple Music | B23: WANTS/Apple Music
A24: disney | B24: WANTS/Disney
A25: Dine out | B25: WANTS/Eat Out | C25: Diagnosis said 'Dine out', the log calls it 'Eat Out' — mapped across the naming mismatch
A26: Loan | B26: NEEDS/Loan
A27: Internet Install | B27: NEEDS/Internet Install | C27: The log's Oct WiFi install fee was tagged House Improvement instead — see that line
A28: House Improvement (Wants) | B28: WANTS/House Improvement | C28: NEW — found in the log, had no Diagnosis line before
A29: Shopping (Wants) | B29: WANTS/Shopping | C29: NEW — found in the log, had no Diagnosis line before
A30: Transportation (Personal, Wants) | B30: WANTS/TranspoPersonal | C30: NEW — found in the log, had no Diagnosis line before
A31: Membership / Software Subscriptions | B31: NEEDS/Membership | C31: NEW — found in the log, had no Diagnosis line before

Sheet Diagnosis
B2: Monthly Income (Malinis na) | C2: =SUM(C3:C7) -> 32500 | E2: DIAGNOSIS
B3: Suweldo (First cut off) | C3: 15500 | E3: Total Monthly Income | F3: =C2 -> 32500
B4: Suweldo (Second cut off) | C4: 17000 | E4: Current Monthly Spend | F4: =C40 -> 15395.48
B5: Suweldo (Third cut off) | E5: Available Cash to Spend | F5: =C2-C40 -> 17104.52
B6: Suweldo (Fourth cut off) | E6: Potential Savings from Cuts | F6: =H40 -> 0
B7: Extra Income (Fixed or Average) | E7: UPDATED: Available cash to spend | F7: =F6+F5 -> 17104.52 | G7: after adjusting your expenses
B10: Expenses | C10: Current Amount | D10: Fixed or Variable | E10: Need or Want | F10: % Income | G10: New Monthly Budget | H10: Monthly Amount Freed
B11: Housing: Rent / Mortgage | C11: =IFERROR(SUMIFS('Oct 2026'!$B$8:$B$67,'Oct 2026'!$F$8:$F$67,VLOOKUP($B11,'Category Map'!$A$3:$B$31,2,FALSE())),0) -> 0 | D11: Fixed | E11: Need | F11: =IFERROR(C11/$C$2,0) -> 0 | H11: =IF(G11="",0,MAX(0,C11-G11)) -> 0
B12: Kuryente | C12: =IFERROR(SUMIFS('Oct 2026'!$B$8:$B$67,'Oct 2026'!$F$8:$F$67,VLOOKUP($B12,'Category Map'!$A$3:$B$31,2,FALSE())),0) -> 0 | D12: Fixed | E12: Need | F12: =IFERROR(C12/$C$2,0) -> 0 | H12: =IF(G12="",0,MAX(0,C12-G12)) -> 0
B13: Tubig | C13: =IFERROR(SUMIFS('Oct 2026'!$B$8:$B$67,'Oct 2026'!$F$8:$F$67,VLOOKUP($B13,'Category Map'!$A$3:$B$31,2,FALSE())),0) -> 0 | D13: Fixed | E13: Need | F13: =IFERROR(C13/$C$2,0) -> 0 | H13: =IF(G13="",0,MAX(0,C13-G13)) -> 0
B14: Internet | C14: =IFERROR(SUMIFS('Oct 2026'!$B$8:$B$67,'Oct 2026'!$F$8:$F$67,VLOOKUP($B14,'Category Map'!$A$3:$B$31,2,FALSE())),0) -> 0 | D14: Fixed | E14: Need | F14: =IFERROR(C14/$C$2,0) -> 0 | H14: =IF(G14="",0,MAX(0,C14-G14)) -> 0
B15: Drinking water | C15: =IFERROR(SUMIFS('Oct 2026'!$B$8:$B$67,'Oct 2026'!$F$8:$F$67,VLOOKUP($B15,'Category Map'!$A$3:$B$31,2,FALSE())),0) -> 40 | D15: Fixed | E15: Need | F15: =IFERROR(C15/$C$2,0) -> 0.0012307692 | H15: =IF(G15="",0,MAX(0,C15-G15)) -> 0
B16: Groceries | C16: =IFERROR(SUMIFS('Oct 2026'!$B$8:$B$67,'Oct 2026'!$F$8:$F$67,VLOOKUP($B16,'Category Map'!$A$3:$B$31,2,FALSE())),0) -> 429.5 | D16: Variable | E16: Need | F16: =IFERROR(C16/$C$2,0) -> 0.013215385 | H16: =IF(G16="",0,MAX(0,C16-G16)) -> 0
B17: Palengke | C17: =IFERROR(SUMIFS('Oct 2026'!$B$8:$B$67,'Oct 2026'!$F$8:$F$67,VLOOKUP($B17,'Category Map'!$A$3:$B$31,2,FALSE())),0) -> 1205.8 | D17: Variable | E17: Need | F17: =IFERROR(C17/$C$2,0) -> 0.037101538 | H17: =IF(G17="",0,MAX(0,C17-G17)) -> 0
B18: Transportation to Work | C18: =IFERROR(SUMIFS('Oct 2026'!$B$8:$B$67,'Oct 2026'!$F$8:$F$67,VLOOKUP($B18,'Category Map'!$A$3:$B$31,2,FALSE())),0) -> 106 | D18: Fixed | E18: Need | F18: =IFERROR(C18/$C$2,0) -> 0.0032615385 | H18: =IF(G18="",0,MAX(0,C18-G18)) -> 0
B19: Healthcare | C19: =IFERROR(SUMIFS('Oct 2026'!$B$8:$B$67,'Oct 2026'!$F$8:$F$67,VLOOKUP($B19,'Category Map'!$A$3:$B$31,2,FALSE())),0) -> 1000 | D19: Fixed | E19: Need | F19: =IFERROR(C19/$C$2,0) -> 0.030769231 | H19: =IF(G19="",0,MAX(0,C19-G19)) -> 0
B20: Education | C20: =IFERROR(SUMIFS('Oct 2026'!$B$8:$B$67,'Oct 2026'!$F$8:$F$67,VLOOKUP($B20,'Category Map'!$A$3:$B$31,2,FALSE())),0) -> 0 | F20: =IFERROR(C20/$C$2,0) -> 0 | H20: =IF(G20="",0,MAX(0,C20-G20)) -> 0
B21: Communication: Prepaid | C21: =IFERROR(SUMIFS('Oct 2026'!$B$8:$B$67,'Oct 2026'!$F$8:$F$67,VLOOKUP($B21,'Category Map'!$A$3:$B$31,2,FALSE())),0) -> 0 | D21: Fixed | E21: Need | F21: =IFERROR(C21/$C$2,0) -> 0 | H21: =IF(G21="",0,MAX(0,C21-G21)) -> 0
B22: Clothing | C22: =IFERROR(SUMIFS('Oct 2026'!$B$8:$B$67,'Oct 2026'!$F$8:$F$67,VLOOKUP($B22,'Category Map'!$A$3:$B$31,2,FALSE())),0) -> 0 | F22: =IFERROR(C22/$C$2,0) -> 0 | H22: =IF(G22="",0,MAX(0,C22-G22)) -> 0
B23: Debt Payment | C23: =IFERROR(SUMIFS('Oct 2026'!$B$8:$B$67,'Oct 2026'!$F$8:$F$67,VLOOKUP($B23,'Category Map'!$A$3:$B$31,2,FALSE())),0) -> 0 | F23: =IFERROR(C23/$C$2,0) -> 0 | H23: =IF(G23="",0,MAX(0,C23-G23)) -> 0
B24: Entertainment | C24: =IFERROR(SUMIFS('Oct 2026'!$B$8:$B$67,'Oct 2026'!$F$8:$F$67,VLOOKUP($B24,'Category Map'!$A$3:$B$31,2,FALSE())),0) -> 970 | D24: Variable | E24: Want | F24: =IFERROR(C24/$C$2,0) -> 0.029846154 | H24: =IF(G24="",0,MAX(0,C24-G24)) -> 0
B25: Special Occasions | C25: =IFERROR(SUMIFS('Oct 2026'!$B$8:$B$67,'Oct 2026'!$F$8:$F$67,VLOOKUP($B25,'Category Map'!$A$3:$B$31,2,FALSE())),0) -> 0 | F25: =IFERROR(C25/$C$2,0) -> 0 | H25: =IF(G25="",0,MAX(0,C25-G25)) -> 0
B26: Government Contributions | C26: =IFERROR(SUMIFS('Oct 2026'!$B$8:$B$67,'Oct 2026'!$F$8:$F$67,VLOOKUP($B26,'Category Map'!$A$3:$B$31,2,FALSE())),0) -> 0 | F26: =IFERROR(C26/$C$2,0) -> 0 | H26: =IF(G26="",0,MAX(0,C26-G26)) -> 0
B27: Emergency Fund | C27: =IFERROR(SUMIFS('Oct 2026'!$B$8:$B$67,'Oct 2026'!$F$8:$F$67,VLOOKUP($B27,'Category Map'!$A$3:$B$31,2,FALSE())),0) -> 5000 | D27: Fixed | E27: Need | F27: =IFERROR(C27/$C$2,0) -> 0.15384615 | H27: =IF(G27="",0,MAX(0,C27-G27)) -> 0
B28: Netflix Subscription | C28: =IFERROR(SUMIFS('Oct 2026'!$B$8:$B$67,'Oct 2026'!$F$8:$F$67,VLOOKUP($B28,'Category Map'!$A$3:$B$31,2,FALSE())),0) -> 0 | F28: =IFERROR(C28/$C$2,0) -> 0 | H28: =IF(G28="",0,MAX(0,C28-G28)) -> 0
B29: Youtube Premium | C29: =IFERROR(SUMIFS('Oct 2026'!$B$8:$B$67,'Oct 2026'!$F$8:$F$67,VLOOKUP($B29,'Category Map'!$A$3:$B$31,2,FALSE())),0) -> 0 | F29: =IFERROR(C29/$C$2,0) -> 0 | H29: =IF(G29="",0,MAX(0,C29-G29)) -> 0
B30: subcription icloud | C30: =IFERROR(SUMIFS('Oct 2026'!$B$8:$B$67,'Oct 2026'!$F$8:$F$67,VLOOKUP($B30,'Category Map'!$A$3:$B$31,2,FALSE())),0) -> 0 | D30: Fixed | E30: Want | F30: =IFERROR(C30/$C$2,0) -> 0 | H30: =IF(G30="",0,MAX(0,C30-G30)) -> 0
B31: Apple Music | C31: =IFERROR(SUMIFS('Oct 2026'!$B$8:$B$67,'Oct 2026'!$F$8:$F$67,VLOOKUP($B31,'Category Map'!$A$3:$B$31,2,FALSE())),0) -> 0 | D31: Fixed | E31: Want | F31: =IFERROR(C31/$C$2,0) -> 0 | H31: =IF(G31="",0,MAX(0,C31-G31)) -> 0
B32: disney | C32: =IFERROR(SUMIFS('Oct 2026'!$B$8:$B$67,'Oct 2026'!$F$8:$F$67,VLOOKUP($B32,'Category Map'!$A$3:$B$31,2,FALSE())),0) -> 0 | F32: =IFERROR(C32/$C$2,0) -> 0 | H32: =IF(G32="",0,MAX(0,C32-G32)) -> 0
B33: Dine out | C33: =IFERROR(SUMIFS('Oct 2026'!$B$8:$B$67,'Oct 2026'!$F$8:$F$67,VLOOKUP($B33,'Category Map'!$A$3:$B$31,2,FALSE())),0) -> 2244 | D33: Variable | E33: Want | F33: =IFERROR(C33/$C$2,0) -> 0.069046154 | H33: =IF(G33="",0,MAX(0,C33-G33)) -> 0
B34: Loan | C34: =IFERROR(SUMIFS('Oct 2026'!$B$8:$B$67,'Oct 2026'!$F$8:$F$67,VLOOKUP($B34,'Category Map'!$A$3:$B$31,2,FALSE())),0) -> 0 | F34: =IFERROR(C34/$C$2,0) -> 0 | H34: =IF(G34="",0,MAX(0,C34-G34)) -> 0
B35: Internet Install | C35: =IFERROR(SUMIFS('Oct 2026'!$B$8:$B$67,'Oct 2026'!$F$8:$F$67,VLOOKUP($B35,'Category Map'!$A$3:$B$31,2,FALSE())),0) -> 0 | D35: Variable | E35: Need | F35: =IFERROR(C35/$C$2,0) -> 0 | H35: =IF(G35="",0,MAX(0,C35-G35)) -> 0
B36: House Improvement (Wants) | C36: =IFERROR(SUMIFS('Oct 2026'!$B$8:$B$67,'Oct 2026'!$F$8:$F$67,VLOOKUP($B36,'Category Map'!$A$3:$B$31,2,FALSE())),0) -> 2912.9 | D36: Variable | E36: Want | F36: =IFERROR(C36/$C$2,0) -> 0.089627692 | H36: =IF(G36="",0,MAX(0,C36-G36)) -> 0
B37: Shopping (Wants) | C37: =IFERROR(SUMIFS('Oct 2026'!$B$8:$B$67,'Oct 2026'!$F$8:$F$67,VLOOKUP($B37,'Category Map'!$A$3:$B$31,2,FALSE())),0) -> 338.5 | D37: Variable | E37: Want | F37: =IFERROR(C37/$C$2,0) -> 0.010415385 | H37: =IF(G37="",0,MAX(0,C37-G37)) -> 0
B38: Transportation (Personal, Wants) | C38: =IFERROR(SUMIFS('Oct 2026'!$B$8:$B$67,'Oct 2026'!$F$8:$F$67,VLOOKUP($B38,'Category Map'!$A$3:$B$31,2,FALSE())),0) -> 434 | D38: Variable | E38: Want | F38: =IFERROR(C38/$C$2,0) -> 0.013353846 | H38: =IF(G38="",0,MAX(0,C38-G38)) -> 0
B39: Membership / Software Subscriptions | C39: =IFERROR(SUMIFS('Oct 2026'!$B$8:$B$67,'Oct 2026'!$F$8:$F$67,VLOOKUP($B39,'Category Map'!$A$3:$B$31,2,FALSE())),0) -> 714.78 | D39: Fixed | E39: Need | F39: =IFERROR(C39/$C$2,0) -> 0.021993231 | H39: =IF(G39="",0,MAX(0,C39-G39)) -> 0
B40: Total | C40: =SUM(C11:C39) -> 15395.48 | F40: =SUM(F11:F39) -> 0.47370708 | G40: =SUM(G11:G39) -> 0 | H40: =SUM(H11:H39) -> 0
B42: Reconciliation check: | C42: =C40-'Oct 2026'!D4 -> 0 | D42: =IF(C42=0,"Matches the raw log exactly","Off by "&TEXT(C42,"#,##0.00")&" vs. the raw log — check for an uncategorized transaction") -> Matches the raw log exactly

Sheet Goals
A2: YOUR SAVINGS GOAL
A3: Savings goal amount | B3: 35000
A4: Already saved toward this goal | B4: 0
A5: SAVINGS GAP | B5: =MAX(B3-B4,0) -> 35000
A6: Target date | B6: sept 30
A7: No. of cutoff until target | B7: 5
A8: Sweldo days per month | B8: 2
A9: SAVINGS NEEDED PER SWELDO DAY | B9: =IFERROR(B5/B7,0) -> 7000
A10: Monthly savings pace | B10: =B9*B8 -> 14000

Sheet Order of Stuff to buy
A1: # | B1: Confirmed? | C1: Plan/Things to Avail this 2026 | E1: Estimated Price | F1: Assuming Date
A2: 1 | B2: =TRUE() -> TRUE | C2: TAC-09CWI/UB2 Aircon (TLC) | E2: 15639 | F2: 46300
A3: 2 | B3: =TRUE() -> TRUE | C3: Smart 5G Max Home WiFi | E3: 2500 | F3: 46305
A4: 3 | B4: =FALSE() -> FALSE | C4: Emergency Fund | E4: 40000 | F4: 46331
A5: 4 | B5: =FALSE() -> FALSE | C5: Teeth Opera | E5: 10000
A6: 5 | B6: =FALSE() -> FALSE | C6: Steel Cabinet | E6: 8000 | F6: 46361
A7: 6 | B7: =FALSE() -> FALSE | C7: Sony Camera | E7: 45000 | F7: 46361
A8: 7 | B8: =FALSE() -> FALSE | C8: Hodekt Mini Washing Machine | E8: 2500
A9: 8 | B9: =FALSE() -> FALSE | C9: Emergency Fund | E9: 40000
A10: 9 | B10: =FALSE() -> FALSE | C10: Shark Hydrovac Vacuum
A11: 10 | B11: =FALSE() -> FALSE | C11: Carpet/Rugs
A12: 11 | B12: =FALSE() -> FALSE | C12: Sofa
A13: 12 | B13: =FALSE() -> FALSE | C13: Bedframe
A14: 13 | B14: =FALSE() -> FALSE
A15: 14 | B15: =FALSE() -> FALSE
A16: 15 | B16: =FALSE() -> FALSE
A17: 16 | B17: =FALSE() -> FALSE
A18: 17 | B18: =FALSE() -> FALSE | C18: Trip to Cebu | E18: 25000 | F18: 46300
A19: 18 | B19: =FALSE() -> FALSE | C19: Trip to Vietnam | E19: 30000
A20: 19 | B20: =FALSE() -> FALSE
B22: TOTAL: | E22: =SUM(E2:E20) -> 218639
B23: Fixed: was =SUMIF(F2:F21,">0") which summed the DATE column by coincidence.

Sheet PLANNED GASTOS
A1: Checkbox | B1: Actual | C1: What was Paid | D1: Expected | E1: Date | F1: Type
A2: =FALSE() -> FALSE | C2: savings
A3: =FALSE() -> FALSE | C3: Foods | D3: 2000
A4: =FALSE() -> FALSE | C4: Foods | D4: 2000
A5: =FALSE() -> FALSE | C5: Brace | D5: 1000
A6: =FALSE() -> FALSE | C6: Apt Rent | D6: 8500
A7: =FALSE() -> FALSE | C7: Electric Bill | D7: 1000
A8: =FALSE() -> FALSE | C8: Wi-Fi Bill | D8: 400
A9: =FALSE() -> FALSE | C9: Transpo to Work | D9: 1000
A10: =FALSE() -> FALSE | C10: Water Bill | D10: 140
A11: =FALSE() -> FALSE | C11: Gym | D11: 2450
A12: =FALSE() -> FALSE | C12: icloud | D12: 179
A13: =FALSE() -> FALSE | C13: apple music | D13: 75
C15: Total Planned: | D15: =SUM(D2:D13) -> 18744
C16: Removed: a disconnected pivot-table remnant that showed a hardcoded 0.

Sheet Savings Tracker
A1: Savings Tracker
H4: Emergency Funds Tracker
B5: EMERGENCY FUNDS | E5: =IFERROR(F10/B10,0) -> 0 | I5: Amount | J5: From
B10: 35000 | F10: 0
B11: Due: | D11: 46331 | F11: =B10-F10 -> 35000
